odoo/addons/sale_shipping_info_helper/README.rst
odoo/addons/sale_shipping_info_helper/__init__.py
odoo/addons/sale_shipping_info_helper/__manifest__.py
odoo/addons/sale_shipping_info_helper/i18n/ca.po
odoo/addons/sale_shipping_info_helper/i18n/de.po
odoo/addons/sale_shipping_info_helper/i18n/el_GR.po
odoo/addons/sale_shipping_info_helper/i18n/es.po
odoo/addons/sale_shipping_info_helper/i18n/es_ES.po
odoo/addons/sale_shipping_info_helper/i18n/es_VE.po
odoo/addons/sale_shipping_info_helper/i18n/fi.po
odoo/addons/sale_shipping_info_helper/i18n/fr.po
odoo/addons/sale_shipping_info_helper/i18n/hr.po
odoo/addons/sale_shipping_info_helper/i18n/hr_HR.po
odoo/addons/sale_shipping_info_helper/i18n/hu.po
odoo/addons/sale_shipping_info_helper/i18n/it.po
odoo/addons/sale_shipping_info_helper/i18n/nl.po
odoo/addons/sale_shipping_info_helper/i18n/nl_NL.po
odoo/addons/sale_shipping_info_helper/i18n/pt.po
odoo/addons/sale_shipping_info_helper/i18n/pt_BR.po
odoo/addons/sale_shipping_info_helper/i18n/ro.po
odoo/addons/sale_shipping_info_helper/i18n/sale_shipping_info_helper.pot
odoo/addons/sale_shipping_info_helper/i18n/sk.po
odoo/addons/sale_shipping_info_helper/i18n/sl.po
odoo/addons/sale_shipping_info_helper/i18n/tr.po
odoo/addons/sale_shipping_info_helper/i18n/tr_TR.po
odoo/addons/sale_shipping_info_helper/i18n/vi_VN.po
odoo/addons/sale_shipping_info_helper/i18n/zh_CN.po
odoo/addons/sale_shipping_info_helper/models/__init__.py
odoo/addons/sale_shipping_info_helper/models/sale_order.py
odoo/addons/sale_shipping_info_helper/readme/CONTRIBUTORS.rst
odoo/addons/sale_shipping_info_helper/readme/DESCRIPTION.rst
odoo/addons/sale_shipping_info_helper/static/description/icon.png
odoo/addons/sale_shipping_info_helper/static/description/index.html
odoo/addons/sale_shipping_info_helper/tests/__init__.py
odoo/addons/sale_shipping_info_helper/tests/test_sale_shipping_info_helper.py
odoo14_addon_sale_shipping_info_helper-14.0.1.0.1.dev11.dist-info/METADATA
odoo14_addon_sale_shipping_info_helper-14.0.1.0.1.dev11.dist-info/WHEEL
odoo14_addon_sale_shipping_info_helper-14.0.1.0.1.dev11.dist-info/top_level.txt
odoo14_addon_sale_shipping_info_helper-14.0.1.0.1.dev11.dist-info/RECORD
